napari_nlm/__init__.py
napari_nlm/_sample_data.py
napari_nlm/_widget.py
napari_nlm/napari.yaml
napari_nlm/_tests/__init__.py
napari_nlm/_tests/test_sample_data.py
napari_nlm/_tests/test_widget.py
napari_nlm-0.0.4.dist-info/LICENSE
napari_nlm-0.0.4.dist-info/METADATA
napari_nlm-0.0.4.dist-info/WHEEL
napari_nlm-0.0.4.dist-info/entry_points.txt
napari_nlm-0.0.4.dist-info/top_level.txt
napari_nlm-0.0.4.dist-info/RECORD
